test_cloud_storage/__init__.py
test_cloud_storage/aws_storage.py
test_cloud_storage/azure_storage.py
test_cloud_storage/gcp_storage.py
test_cloud_storage/storage_manager.py
test_cloud_storage-0.6.6.dist-info/LICENSE
test_cloud_storage-0.6.6.dist-info/METADATA
test_cloud_storage-0.6.6.dist-info/WHEEL
test_cloud_storage-0.6.6.dist-info/top_level.txt
test_cloud_storage-0.6.6.dist-info/RECORD
