Metadata-Version: 2.1
Name: test_cloud_storage
Version: 0.6.6
Summary: A unified cloud storage package for AWS, Azure, and GCP
Author: Aaditya Muleva
Author-email: aaditya.muleva@trovehealth.io
License: MIT
Classifier: Programming Language :: Python :: 3
Classifier: License :: OSI Approved :: MIT License
Classifier: Operating System :: OS Independent
Requires-Python: >=3.6
License-File: LICENSE
Requires-Dist: boto3
